html_image_embedder/__init__.py
html_image_embedder/html_image_embedder.py
html_image_embedder-1.0.0.dist-info/METADATA
html_image_embedder-1.0.0.dist-info/WHEEL
html_image_embedder-1.0.0.dist-info/licenses/LICENSE
html_image_embedder-1.0.0.dist-info/RECORD
