Metadata-Version: 2.1
Name: html_image_embedder
Version: 1.0.0
Summary: Converts images to base64 and embeds them in HTML files.
Project-URL: Homepage, https://github.com/matthew-hajec/html_image_embedder
Project-URL: Issues, https://github.com/matthew-hajec/html_image_embedder/issues
Author-email: Matthew Hajec <matthew.hajec02@gmail.com>
License-File: LICENSE
Classifier: License :: OSI Approved :: MIT License
Classifier: Operating System :: OS Independent
Classifier: Programming Language :: Python :: 3
Requires-Python: >=3.7
Requires-Dist: selectolax>=0.3
